brihome/__init__.py
python_brihome-0.0.3.dist-info/LICENSE
python_brihome-0.0.3.dist-info/METADATA
python_brihome-0.0.3.dist-info/WHEEL
python_brihome-0.0.3.dist-info/top_level.txt
python_brihome-0.0.3.dist-info/RECORD
