Metadata-Version: 2.1
Name: python-brihome
Version: 0.0.3
Summary: A small package to control Brihome smart led bulbs.
Home-page: https://github.com/juliusmh/python-brihome
Author: Julius Hinze
Author-email: juliusmh@web.de
License: UNKNOWN
Platform: UNKNOWN
Classifier: Programming Language :: Python :: 3
Classifier: License :: OSI Approved :: MIT License
Classifier: Operating System :: OS Independent
Requires-Dist: pytuya (==7.0.2)
